[{
	"Fcat": {
		"Begda": "/Date(1218285579000)/",
		"Endda": "/Date(1339677579000)/",
		"BenDes": "BenDes 1",
		"Icon": "Icon 1",
		"EffecOn": "/Date(1224160779000)/",
		"UnitSel": 5219,
		"UnitMin": 2156,
		"UnitMax": 4178,
		"UnitBud": 4209,
		"UnitCal": 7175,
		"DaysSel": 7215.3,
		"DaysRem": 8096.76,
		"DaysCal": 1956.85,
		"DaysMin": 2198,
		"DaysMax": 113.33,
		"DaysRate": 9253,
		"ValuCal": "ValuCal 1",
		"OptsCos": "OptsCos 1",
		"OptsCal": 950,
		"Url": "Url 1"
	},
	"UISettings": {
		"Tab1": true,
		"Tab2": true,
		"Tab3": true,
		"Tab4": false,
		"Tab1Hand": "Tab1Hand 1",
		"Tab2Hand": "Tab2Hand 1",
		"Tab3Hand": "Tab3Hand 1",
		"Tab4Hand": "Tab4Hand 1",
		"Tab1Icon": "Tab1Icon 1",
		"Tab2Icon": "Tab2Icon 1",
		"Tab3Icon": "Tab3Icon 1",
		"Tab4Icon": "Tab4Icon 1",
		"Tab1Label": "Tab1Label 1",
		"Tab2Label": "Tab2Label 1",
		"Tab3Label": "Tab3Label 1",
		"Tab4Label": "Tab4Label 1",
		"Tab1Fcat": "Tab1Fcat 1",
		"Tab2Fcat": "Tab2Fcat 1",
		"Tab3Fcat": "Tab3Fcat 1",
		"Tab4Fcat": "Tab4Fcat 1",
		"Lowbut1": "Lowbut1 1",
		"Lowbut2": "Lowbut2 1",
		"Lowbut3": "Lowbut3 1",
		"Lowbut4": "Lowbut4 1",
		"Lowbut1Icon": "Lowbut1Icon 1",
		"Lowbut2Icon": "Lowbut2Icon 1",
		"Lowbut3Icon": "Lowbut3Icon 1",
		"Lowbut4Icon": "Lowbut4Icon 1",
		"Lowbut1Label": "Lowbut1Label 1",
		"Lowbut2Label": "Lowbut2Label 1",
		"Lowbut3Label": "Lowbut3Label 1",
		"Lowbut4Label": "Lowbut4Label 1",
		"Lowbut1Hand": "Lowbut1Hand 1",
		"Lowbut2Hand": "Lowbut2Hand 1",
		"Lowbut3Hand": "Lowbut3Hand 1",
		"Lowbut4Hand": "Lowbut4Hand 1",
		"Heabut1": "Heabut1 1",
		"Heabut2": "Heabut2 1",
		"Heabut3": "Heabut3 1",
		"Heabut4": "Heabut4 1",
		"Heabut1Icon": "Heabut1Icon 1",
		"Heabut2Icon": "Heabut2Icon 1",
		"Heabut3Icon": "Heabut3Icon 1",
		"Heabut4Icon": "Heabut4Icon 1",
		"Heabut1Label": "Heabut1Label 1",
		"Heabut2Label": "Heabut2Label 1",
		"Heabut3Label": "Heabut3Label 1",
		"Heabut4Label": "Heabut4Label 1",
		"Heabut1Hand": "Heabut1Hand 1",
		"Heabut2Hand": "Heabut2Hand 1",
		"Heabut3Hand": "Heabut3Hand 1",
		"Heabut4Hand": "Heabut4Hand 1"
	},
	"Messg": {
		"Msgid": "Msgid 1",
		"Msgty": "Msgty 1",
		"Msgno": "Msgno 1",
		"Msgv1": "Msgv1 1",
		"Msgv2": "Msgv2 1",
		"Msgv3": "Msgv3 1",
		"Msgv4": "Msgv4 1"
	},
	"Pernr": "39910",
	"Actionid": "5416151111",
	"Barea": "BARE1",
	"Bplan": "BPLA2",
	"FrontendItem": "651165461",
	"Status": "01"
}]